ffolayer/__init__.py
ffolayer/ffocp_eq.py
ffolayer/ffoqp.py
ffolayer/ffoqp_eq.py
ffolayer/utils.py
ffolayer-0.1.2.dist-info/METADATA
ffolayer-0.1.2.dist-info/WHEEL
ffolayer-0.1.2.dist-info/licenses/LICENSE
ffolayer-0.1.2.dist-info/RECORD
