Metadata-Version: 2.4
Name: ffolayer
Version: 0.1.2
Summary: A fully first-order (FFO) layer for differentiable convex optimization
Project-URL: Homepage, https://github.com/GT-KOALA/FFOLayer
Project-URL: Repository, https://github.com/GT-KOALA/FFOLayer.git
Project-URL: Documentation, https://github.com/GT-KOALA/FFOLayer
Author: Zihao Zhao, Kai-Chia Mo, Shing-Hei Ho, Brandon Amos, Kai Wang
License: MIT
License-File: LICENSE
Keywords: convex optimization,differentiable optimization,first-order
Requires-Python: >=3.9
Requires-Dist: cvxpy
Requires-Dist: diffcp
Requires-Dist: numpy
Requires-Dist: scipy
Requires-Dist: threadpoolctl
Requires-Dist: torch
